{
  "project_info": {
    "project_number": "765865518853",
    "project_id": "notesapp1st",
    "storage_bucket": "notesapp1st.firebasestorage.app"
  },
  "client": [
    {
      "client_info": {
        "mobilesdk_app_id": "1:765865518853:android:237f81cc4c702c407a796c",
        "android_client_info": {
          "package_name": "com.example.finishapplication1"
        }
      },
      "oauth_client": [],
      "api_key": [
        {
          "current_key": "AIzaSyCdlHzGHA4uc7theGSvIIKzpxwWNMLm_Oc"
        }
      ],
      "services": {
        "appinvite_service": {
          "other_platform_oauth_client": []
        }
      }
    }
  ],
  "configuration_version": "1"
}